erc8004/__init__.py
erc8004/client.py
erc8004/identity.py
erc8004/reputation.py
erc8004/types.py
erc8004/validation.py
erc8004/abis/IdentityRegistry.json
erc8004/abis/ReputationRegistry.json
erc8004/abis/ValidationRegistry.json
erc8004/adapters/__init__.py
erc8004/adapters/base.py
erc8004/adapters/web3_adapter.py
erc8004/utils/__init__.py
erc8004/utils/ipfs.py
erc_8004_py-1.0.0.dist-info/licenses/LICENSE
erc_8004_py-1.0.0.dist-info/METADATA
erc_8004_py-1.0.0.dist-info/WHEEL
erc_8004_py-1.0.0.dist-info/top_level.txt
erc_8004_py-1.0.0.dist-info/RECORD
