Metadata-Version: 2.4
Name: erc-8004-py
Version: 1.0.0
Summary: Python SDK for ERC-8004 Trustless Agents protocol
Author: ERC-8004 Contributors
License: MIT
Project-URL: Homepage, https://github.com/tetratorus/sdk
Project-URL: Documentation, https://github.com/tetratorus/sdk
Project-URL: Repository, https://github.com/tetratorus/sdk
Project-URL: Bug Tracker, https://github.com/tetratorus/sdk/issues
Keywords: erc8004,agents,reputation,validation,blockchain,ethereum
Classifier: Development Status :: 3 - Alpha
Classifier: Intended Audience :: Developers
Classifier: License :: OSI Approved :: MIT License
Classifier: Programming Language :: Python :: 3
Classifier: Programming Language :: Python :: 3.8
Classifier: Programming Language :: Python :: 3.9
Classifier: Programming Language :: Python :: 3.10
Classifier: Programming Language :: Python :: 3.11
Classifier: Programming Language :: Python :: 3.12
Classifier: Topic :: Software Development :: Libraries :: Python Modules
Requires-Python: >=3.8
License-File: LICENSE
Requires-Dist: web3>=6.0.0
Requires-Dist: requests>=2.28.0
Requires-Dist: typing-extensions>=4.0.0
Provides-Extra: dev
Requires-Dist: pytest>=7.0.0; extra == "dev"
Requires-Dist: pytest-asyncio>=0.21.0; extra == "dev"
Requires-Dist: black>=23.0.0; extra == "dev"
Requires-Dist: mypy>=1.0.0; extra == "dev"
Requires-Dist: flake8>=6.0.0; extra == "dev"
Requires-Dist: python-dotenv>=1.0.0; extra == "dev"
Dynamic: license-file
